config/__init__.py
terragen/__init__.py
terragen/cli.py
terragen/providers/__init__.py
terragen/providers/cloud_provider.py
terragen/providers/aws/__init__.py
terragen/providers/aws/aws_provider.py
terragen/providers/aws/app/__init__.py
terragen/providers/aws/app/terraform_factory.py
terragen/providers/aws/app/terraform_launcher.py
terragen/providers/aws/app/utils.py
terragen/providers/aws/models/__init__.py
terragen/providers/aws/models/aws_models.py
terragen/providers/aws/templates/__init__.py
terragen/providers/aws/templates/config.jinja
terragen/providers/aws/templates/tfvars.jinja
terragen-0.4.0.dist-info/LICENSE
terragen-0.4.0.dist-info/METADATA
terragen-0.4.0.dist-info/WHEEL
terragen-0.4.0.dist-info/entry_points.txt
terragen-0.4.0.dist-info/top_level.txt
terragen-0.4.0.dist-info/RECORD
