Metadata-Version: 2.1
Name: terragen
Version: 0.4.0
Summary: Configure, generate and apply Terraform modules to create and destroy Cloud Infrastructure
Home-page: https://github.com/hunt3ri/terragen
Author: Iain Hunter
Author-email: iain.hunter@outlook.com
License: MIT
Platform: UNKNOWN
Classifier: License :: OSI Approved :: MIT License
Classifier: Programming Language :: Python
Classifier: Programming Language :: Python :: 3
Classifier: Programming Language :: Python :: 3.8
Classifier: Programming Language :: Python :: Implementation :: CPython
Classifier: Programming Language :: Python :: Implementation :: PyPy
Requires-Python: >=3.8.0
License-File: LICENSE
Requires-Dist: attrs
Requires-Dist: hydra-core
Requires-Dist: Jinja2
Requires-Dist: python-dotenv
Requires-Dist: toml
